esctl/__init__.py
esctl/commands.py
esctl/config.py
esctl/elasticsearch.py
esctl/exceptions.py
esctl/formatter.py
esctl/interactive.py
esctl/main.py
esctl/override.py
esctl/settings.py
esctl/utils.py
esctl/cmd/__init__.py
esctl/cmd/alias.py
esctl/cmd/cat.py
esctl/cmd/cluster.py
esctl/cmd/config.py
esctl/cmd/document.py
esctl/cmd/index.py
esctl/cmd/logging.py
esctl/cmd/node.py
esctl/cmd/raw.py
esctl/cmd/repository.py
esctl/cmd/roles.py
esctl/cmd/settings.py
esctl/cmd/snapshot.py
esctl/cmd/task.py
esctl/cmd/users.py
esctl-1.9.0.dist-info/LICENSE
esctl-1.9.0.dist-info/METADATA
esctl-1.9.0.dist-info/WHEEL
esctl-1.9.0.dist-info/entry_points.txt
esctl-1.9.0.dist-info/namespace_packages.txt
esctl-1.9.0.dist-info/top_level.txt
esctl-1.9.0.dist-info/RECORD
