Metadata-Version: 2.1
Name: esctl
Version: 1.9.0
Summary: Easy to use CLI tool to manage Elasticsearch, preventing long curl commands.
Home-page: https://github.com/jeromepin/esctl
Author: Jérôme Pin
Maintainer: Jérôme Pin
License: UNKNOWN
Keywords: elasticsearch,es,cli
Platform: Any
Classifier: Development Status :: 5 - Production/Stable
Classifier: Environment :: Console
Classifier: Intended Audience :: Developers
Classifier: Intended Audience :: System Administrators
Classifier: License :: OSI Approved :: GNU General Public License v3 (GPLv3)
Classifier: Operating System :: OS Independent
Classifier: Programming Language :: Python
Classifier: Programming Language :: Python :: 3.6
Classifier: Programming Language :: Python :: 3.7
Classifier: Programming Language :: Python :: 3.8
Classifier: Topic :: Utilities
Classifier: Topic :: System :: Shells
License-File: LICENSE
Requires-Dist: cerberus (==1.3.2)
Requires-Dist: certifi
Requires-Dist: cliff (==3.0)
Requires-Dist: elasticsearch
Requires-Dist: jmespath (==0.10.0)
